{
  "mappings": {
    "properties": {
      "frenchTitle": {
        "type": "text",
        "analyzer": "french"
      },

      "title": {
        "type": "text",
        "analyzer": "english"
      },
      "description": {
        "type": "text",
        "analyzer": "english"
      },

      "abilities": {
        "type": "text",
        "fields": {
          "exact": {
            "type": "keyword"
          }
        }
      },
      "artists": {
        "type": "text",
        "fields": {
          "exact": {
            "type": "keyword"
          }
        }
      },
      "colors": {
        "type": "text",
        "fields": {
          "exact": {
            "type": "keyword"
          }
        }
      },
      "dualColors": {
        "type": "text",
        "fields": {
          "exact": {
            "type": "keyword"
          }
        }
      },
      "tripleColors": {
        "type": "text",
        "fields": {
          "exact": {
            "type": "keyword"
          }
        }
      },
      "editions": {
        "type": "text",
        "fields": {
          "exact": {
            "type": "keyword"
          }
        }
      },
      "formats": {
        "type": "text",
        "fields": {
          "exact": {
            "type": "keyword"
          }
        }
      },
      "priceRanges": {
        "type": "text",
        "fields": {
          "exact": {
            "type": "keyword"
          }
        }
      },
      "blocks": {
        "type": "text",
        "fields": {
          "exact": {
            "type": "keyword"
          }
        }
      },
      "layout": {
        "type": "text",
        "fields": {
          "exact": {
            "type": "keyword"
          }
        }
      },
      "special": {
        "type": "text",
        "fields": {
          "exact": {
            "type": "keyword"
          }
        }
      },
      "land": {
        "type": "text",
        "fields": {
          "exact": {
            "type": "keyword"
          }
        }
      },
      "type": {
        "type": "text",
        "fielddata": true
      },
      "rarities": {
        "type": "text",
        "fielddata": true
      },

      "power": {
        "type": "keyword"
      },
      "toughness": {
        "type": "keyword"
      }
    }
  }
}
